baseline_optimal/__init__.py
baseline_optimal/_classifier.py
baseline_optimal/_processor.py
baseline_optimal/class_task.py
baseline_optimal/classifier_pipeline.py
baseline_optimal-0.0.5.dist-info/LICENSE
baseline_optimal-0.0.5.dist-info/METADATA
baseline_optimal-0.0.5.dist-info/WHEEL
baseline_optimal-0.0.5.dist-info/top_level.txt
baseline_optimal-0.0.5.dist-info/RECORD
